odoo10_addon_mail_drop_target-10.0.1.0.1-py3.8-nspkg.pth
odoo/addons/mail_drop_target/README.rst
odoo/addons/mail_drop_target/__init__.py
odoo/addons/mail_drop_target/__manifest__.py
odoo/addons/mail_drop_target/i18n/mail_drop_target.pot
odoo/addons/mail_drop_target/models/__init__.py
odoo/addons/mail_drop_target/models/mail_thread.py
odoo/addons/mail_drop_target/static/description/icon.png
odoo/addons/mail_drop_target/static/src/css/mail_drop_target.css
odoo/addons/mail_drop_target/static/src/js/mail_drop_target.js
odoo/addons/mail_drop_target/tests/__init__.py
odoo/addons/mail_drop_target/tests/sample.eml
odoo/addons/mail_drop_target/tests/sample.msg
odoo/addons/mail_drop_target/tests/test_mail_drop_target.py
odoo/addons/mail_drop_target/views/templates.xml
odoo10_addon_mail_drop_target-10.0.1.0.1.dist-info/METADATA
odoo10_addon_mail_drop_target-10.0.1.0.1.dist-info/WHEEL
odoo10_addon_mail_drop_target-10.0.1.0.1.dist-info/namespace_packages.txt
odoo10_addon_mail_drop_target-10.0.1.0.1.dist-info/top_level.txt
odoo10_addon_mail_drop_target-10.0.1.0.1.dist-info/RECORD
